<?xml version="1.0" encoding="UTF-8"?>
<crossword-compiler-applet xmlns="http://crossword.info/xml/crossword-compiler-applet"><applet-settings width="755" height="583" cursor-color="#FFFF00" wrong-letter-color="#FF0000" selected-cells-color="#C0C0C0" hide-numbers="false" clue-float-background="#000000" pencil-color="#000000"><clues layout="right" font-family="SansSerif" font-size="11" width="200" gutter="5" selection-color="#FF0000" bold-numbers="true" right-align-numbers="false" period-with-numbers="true" completed-color="#000000"/><actions buttons-layout="left" wide-buttons="false" graphical-buttons="false"/><completion friendly-submit="false" only-if-correct="true">Čestitamo, rešili ste!</completion><title>VUS     Križanka</title><copyright>©VUS                                                                   copyright@flask2.onrender.com</copyright></applet-settings><rectangular-puzzle xmlns="http://crossword.info/xml/rectangular-puzzle" alphabet="ABCDEFGHIJKLMNOPQRSTUVWXYZ"><metadata><title></title><creator></creator><copyright></copyright><description></description></metadata><crossword><grid width="17" height="17"><grid-look italian-style="true" thick-border="true" numbering-scheme="normal" cell-size-in-pixels="32" block-color="#000080"/><cell x="1" y="1" solution="K" number="1"/><cell x="1" y="2" solution="V" number="16"/><cell x="1" y="3" solution="A" number="19"/><cell x="1" y="4" solution="R" number="22"/><cell x="1" y="5" solution="K" number="26"/><cell x="1" y="6" type="block"/><cell x="1" y="7" solution="Š" number="37"/><cell x="1" y="8" solution="A" number="43"/><cell x="1" y="9" solution="C" number="46"/><cell x="1" y="10" type="block"/><cell x="1" y="11" solution="B" number="56"/><cell x="1" y="12" solution="E" number="62"/><cell x="1" y="13" solution="N" number="65"/><cell x="1" y="14" solution="A" number="72"/><cell x="1" y="15" solution="R" number="79"/><cell x="1" y="16" solution="E" number="84"/><cell x="1" y="17" solution="S" number="87"/><cell x="2" y="1" solution="V" number="2"/><cell x="2" y="2" solution="A"/><cell x="2" y="3" solution="R"/><cell x="2" y="4" solution="E"/><cell x="2" y="5" solution="Š"/><cell x="2" y="6" type="block"/><cell x="2" y="7" solution="P" number="38"/><cell x="2" y="8" solution="E"/><cell x="2" y="9" solution="I"/><cell x="2" y="10" type="block"/><cell x="2" y="11" solution="E" number="57"/><cell x="2" y="12" solution="T"/><cell x="2" y="13" solution="A"/><cell x="2" y="14" solution="T"/><cell x="2" y="15" solution="I"/><cell x="2" y="16" solution="S"/><cell x="2" y="17" solution="T"/><cell x="3" y="1" solution="A" number="3"/><cell x="3" y="2" solution="R"/><cell x="3" y="3" solution="A"/><cell x="3" y="4" solution="M"/><cell x="3" y="5" solution="E"/><cell x="3" y="6" type="block"/><cell x="3" y="7" solution="A" number="39"/><cell x="3" y="8" solution="D"/><cell x="3" y="9" solution="U"/><cell x="3" y="10" solution="L" number="53"/><cell x="3" y="11" solution="T"/><cell x="3" y="12" solution="E"/><cell x="3" y="13" solution="R"/><cell x="3" y="14" solution="A"/><cell x="3" y="15" solution="T"/><cell x="3" y="16" solution="O"/><cell x="3" y="17" solution="R"/><cell x="4" y="1" solution="D" number="4"/><cell x="4" y="2" solution="I"/><cell x="4" y="3" solution="N"/><cell x="4" y="4" type="block"/><cell x="4" y="5" solution="F" number="27"/><cell x="4" y="6" solution="L" number="32"/><cell x="4" y="7" solution="N"/><cell x="4" y="8" type="block"/><cell x="4" y="9" solution="D" number="47"/><cell x="4" y="10" solution="A"/><cell x="4" y="11" solution="I"/><cell x="4" y="12" solution="R"/><cell x="4" y="13" solution="E"/><cell x="4" y="14" type="block"/><cell x="4" y="15" type="block"/><cell x="4" y="16" type="block"/><cell x="4" y="17" type="block"/><cell x="5" y="1" solution="R" number="5"/><cell x="5" y="2" solution="O"/><cell x="5" y="3" solution="D"/><cell x="5" y="4" type="block"/><cell x="5" y="5" solution="T" number="28"/><cell x="5" y="6" solution="I"/><cell x="5" y="7" solution="S"/><cell x="5" y="8" solution="K" number="44"/><cell x="5" y="9" solution="A"/><cell x="5" y="10" solution="R"/><cell x="5" y="11" type="block"/><cell x="5" y="12" type="block"/><cell x="5" y="13" solution="K" number="66"/><cell x="5" y="14" solution="N" number="73"/><cell x="5" y="15" solution="A" number="80"/><cell x="5" y="16" solution="V" number="85"/><cell x="5" y="17" solution="S" number="88"/><cell x="6" y="1" solution="I" number="6"/><cell x="6" y="2" solution="L"/><cell x="6" y="3" solution="A"/><cell x="6" y="4" solution="M" number="23"/><cell x="6" y="5" type="block"/><cell x="6" y="6" solution="Š" number="33"/><cell x="6" y="7" solution="K"/><cell x="6" y="8" solution="U"/><cell x="6" y="9" solution="D"/><cell x="6" y="10" type="block"/><cell x="6" y="11" solution="R" number="58"/><cell x="6" y="12" solution="E" number="63"/><cell x="6" y="13" solution="O"/><cell x="6" y="14" solution="S"/><cell x="6" y="15" solution="T"/><cell x="6" y="16" solution="A"/><cell x="6" y="17" solution="T"/><cell x="7" y="1" solution="G" number="7"/><cell x="7" y="2" solution="I"/><cell x="7" y="3" solution="D"/><cell x="7" y="4" solution="E"/><cell x="7" y="5" type="block"/><cell x="7" y="6" solution="P" number="34"/><cell x="7" y="7" solution="A"/><cell x="7" y="8" solution="N"/><cell x="7" y="9" solution="D"/><cell x="7" y="10" type="block"/><cell x="7" y="11" solution="D" number="59"/><cell x="7" y="12" solution="I"/><cell x="7" y="13" solution="V"/><cell x="7" y="14" solution="U"/><cell x="7" y="15" solution="L"/><cell x="7" y="16" solution="J"/><cell x="7" y="17" solution="E"/><cell x="8" y="1" solution="A" number="8"/><cell x="8" y="2" solution="T"/><cell x="8" y="3" solution="E"/><cell x="8" y="4" solution="J"/><cell x="8" y="5" type="block"/><cell x="8" y="6" type="block"/><cell x="8" y="7" solution="S" number="40"/><cell x="8" y="8" solution="A"/><cell x="8" y="9" solution="E"/><cell x="8" y="10" type="block"/><cell x="8" y="11" solution="E" number="60"/><cell x="8" y="12" solution="S"/><cell x="8" y="13" solution="A"/><cell x="8" y="14" type="block"/><cell x="8" y="15" solution="A" number="81"/><cell x="8" y="16" solution="T"/><cell x="8" y="17" solution="P"/><cell x="9" y="1" type="block"/><cell x="9" y="2" type="block"/><cell x="9" y="3" solution="D" number="20"/><cell x="9" y="4" solution="E"/><cell x="9" y="5" solution="D" number="29"/><cell x="9" y="6" type="block"/><cell x="9" y="7" solution="T" number="41"/><cell x="9" y="8" solution="R"/><cell x="9" y="9" solution="G"/><cell x="9" y="10" solution="A" number="54"/><cell x="9" y="11" solution="Č"/><cell x="9" y="12" type="block"/><cell x="9" y="13" solution="J" number="67"/><cell x="9" y="14" solution="E" number="74"/><cell x="9" y="15" solution="N"/><cell x="9" y="16" type="block"/><cell x="9" y="17" type="block"/><cell x="10" y="1" solution="I" number="9"/><cell x="10" y="2" solution="A" number="17"/><cell x="10" y="3" solution="U"/><cell x="10" y="4" type="block"/><cell x="10" y="5" solution="E" number="30"/><cell x="10" y="6" solution="W" number="35"/><cell x="10" y="7" solution="E"/><cell x="10" y="8" type="block"/><cell x="10" y="9" solution="U" number="48"/><cell x="10" y="10" solution="R"/><cell x="10" y="11" solution="E"/><cell x="10" y="12" type="block"/><cell x="10" y="13" type="block"/><cell x="10" y="14" solution="R" number="75"/><cell x="10" y="15" solution="T"/><cell x="10" y="16" solution="A" number="86"/><cell x="10" y="17" solution="Č" number="89"/><cell x="11" y="1" solution="Z" number="10"/><cell x="11" y="2" solution="V"/><cell x="11" y="3" solution="E"/><cell x="11" y="4" solution="Z" number="24"/><cell x="11" y="5" solution="D"/><cell x="11" y="6" solution="A"/><cell x="11" y="7" solution="N"/><cell x="11" y="8" type="block"/><cell x="11" y="9" solution="A" number="49"/><cell x="11" y="10" solution="B"/><cell x="11" y="11" solution="A"/><cell x="11" y="12" solution="K" number="64"/><cell x="11" y="13" type="block"/><cell x="11" y="14" solution="I" number="76"/><cell x="11" y="15" solution="S"/><cell x="11" y="16" solution="L"/><cell x="11" y="17" solution="A"/><cell x="12" y="1" solution="B" number="11"/><cell x="12" y="2" solution="A"/><cell x="12" y="3" solution="R"/><cell x="12" y="4" solution="I"/><cell x="12" y="5" solution="E"/><cell x="12" y="6" solution="R"/><cell x="12" y="7" solution="A"/><cell x="12" y="8" type="block"/><cell x="12" y="9" solution="T" number="50"/><cell x="12" y="10" solution="U"/><cell x="12" y="11" solution="R"/><cell x="12" y="12" solution="N"/><cell x="12" y="13" type="block"/><cell x="12" y="14" solution="E" number="77"/><cell x="12" y="15" solution="K"/><cell x="12" y="16" solution="A"/><cell x="12" y="17" solution="R"/><cell x="13" y="1" solution="A" number="12"/><cell x="13" y="2" solution="N"/><cell x="13" y="3" solution="O"/><cell x="13" y="4" solution="U"/><cell x="13" y="5" solution="K"/><cell x="13" y="6" type="block"/><cell x="13" y="7" type="block"/><cell x="13" y="8" solution="H" number="45"/><cell x="13" y="9" solution="E"/><cell x="13" y="10" solution="N"/><cell x="13" y="11" solution="M"/><cell x="13" y="12" solution="A"/><cell x="13" y="13" solution="N" number="68"/><cell x="13" y="14" type="block"/><cell x="13" y="15" solution="I" number="82"/><cell x="13" y="16" solution="S"/><cell x="13" y="17" solution="O"/><cell x="14" y="1" type="block"/><cell x="14" y="2" type="block"/><cell x="14" y="3" type="block"/><cell x="14" y="4" type="block"/><cell x="14" y="5" solution="M" number="31"/><cell x="14" y="6" solution="O" number="36"/><cell x="14" y="7" solution="D" number="42"/><cell x="14" y="8" solution="E"/><cell x="14" y="9" solution="M"/><cell x="14" y="10" type="block"/><cell x="14" y="11" solution="E" number="61"/><cell x="14" y="12" solution="P"/><cell x="14" y="13" solution="I"/><cell x="14" y="14" type="block"/><cell x="14" y="15" solution="P" number="83"/><cell x="14" y="16" solution="E"/><cell x="14" y="17" solution="V"/><cell x="15" y="1" solution="T" number="13"/><cell x="15" y="2" solution="O" number="18"/><cell x="15" y="3" solution="V" number="21"/><cell x="15" y="4" solution="A" number="25"/><cell x="15" y="5" solution="R"/><cell x="15" y="6" solution="N"/><cell x="15" y="7" solution="A"/><cell x="15" y="8" solution="S"/><cell x="15" y="9" solution="A"/><cell x="15" y="10" solution="N" number="55"/><cell x="15" y="11" solution="J"/><cell x="15" y="12" type="block"/><cell x="15" y="13" solution="S" number="69"/><cell x="15" y="14" solution="P" number="78"/><cell x="15" y="15" solution="A"/><cell x="15" y="16" solution="H"/><cell x="15" y="17" solution="I"/><cell x="16" y="1" solution="O" number="14"/><cell x="16" y="2" solution="V"/><cell x="16" y="3" solution="E"/><cell x="16" y="4" solution="R"/><cell x="16" y="5" solution="A"/><cell x="16" y="6" solution="T"/><cell x="16" y="7" solution="H"/><cell x="16" y="8" type="block"/><cell x="16" y="9" solution="L" number="51"/><cell x="16" y="10" solution="E"/><cell x="16" y="11" solution="E"/><cell x="16" y="12" type="block"/><cell x="16" y="13" solution="A" number="70"/><cell x="16" y="14" solution="S"/><cell x="16" y="15" solution="K"/><cell x="16" y="16" solution="I"/><cell x="16" y="17" solution="N"/><cell x="17" y="1" solution="P" number="15"/><cell x="17" y="2" solution="A"/><cell x="17" y="3" solution="R"/><cell x="17" y="4" solution="A"/><cell x="17" y="5" solution="Z"/><cell x="17" y="6" solution="O"/><cell x="17" y="7" solution="L"/><cell x="17" y="8" type="block"/><cell x="17" y="9" solution="A" number="52"/><cell x="17" y="10" solution="R"/><cell x="17" y="11" solution="C"/><cell x="17" y="12" type="block"/><cell x="17" y="13" solution="N" number="71"/><cell x="17" y="14" solution="I"/><cell x="17" y="15" solution="T"/><cell x="17" y="16" solution="R"/><cell x="17" y="17" solution="A"/></grid><word id="1" x="1-8" y="1" solution="KVADRIGA" is-theme="true"/><word id="2" x="10-13" y="1" solution="IZBA" is-theme="true"/><word id="3" x="15-17" y="1" solution="TOP" is-theme="true"/><word id="4" x="1-8" y="2" solution="VARIOLIT" is-theme="true"/><word id="5" x="10-13" y="2" solution="AVAN" is-theme="true"/><word id="6" x="15-17" y="2" solution="OVA" is-theme="true"/><word id="7" x="1-13" y="3" solution="ARANDA DE DUERO" is-theme="true"/><word id="8" x="15-17" y="3" solution="VER" is-theme="true"/><word id="9" x="1-3" y="4" solution="REM" is-theme="true"/><word id="10" x="6-9" y="4" solution="MEJE" is-theme="true"/><word id="11" x="11-13" y="4" solution="ZIU" is-theme="true"/><word id="12" x="15-17" y="4" solution="ARA" is-theme="true"/><word id="13" x="1-5" y="5" solution="KŠEFT" is-theme="true"/><word id="14" x="9-17" y="5" solution="DEDEK MRAZ" is-theme="true"/><word id="15" x="4-7" y="6" solution="LIŠP" is-theme="true"/><word id="16" x="10-12" y="6" solution="WAR" is-theme="true"/><word id="17" x="14-17" y="6" solution="ONTO" is-theme="true"/><word id="18" x="1-12" y="7" solution="ŠPANSKA STENA" is-theme="true"/><word id="19" x="14-17" y="7" solution="DAHL" is-theme="true"/><word id="20" x="1-3" y="8" solution="AED" is-theme="true"/><word id="21" x="5-9" y="8" solution="KUNAR" is-theme="true"/><word id="22" x="13-15" y="8" solution="HES" is-theme="true"/><word id="23" x="1-17" y="9" solution="CIUDAD DE GUATEMALA" is-theme="true"/><word id="24" x="3-5" y="10" solution="LAR" is-theme="true"/><word id="25" x="9-13" y="10" solution="ARBUN" is-theme="true"/><word id="26" x="15-17" y="10" solution="NER" is-theme="true"/><word id="27" x="1-4" y="11" solution="BETI" is-theme="true"/><word id="28" x="6-17" y="11" solution="RDEČEARMEJEC" is-theme="true"/><word id="29" x="1-4" y="12" solution="ETER" is-theme="true"/><word id="30" x="6-8" y="12" solution="EIS" is-theme="true"/><word id="31" x="11-14" y="12" solution="KNAP" is-theme="true"/><word id="32" x="1-9" y="13" solution="NAREKOVAJ" is-theme="true"/><word id="33" x="13-17" y="13" solution="NISAN" is-theme="true"/><word id="34" x="1-3" y="14" solution="ATA" is-theme="true"/><word id="35" x="5-7" y="14" solution="NSU" is-theme="true"/><word id="36" x="9-12" y="14" solution="ERIE" is-theme="true"/><word id="37" x="15-17" y="14" solution="PSI" is-theme="true"/><word id="38" x="1-3" y="15" solution="RIT" is-theme="true"/><word id="39" x="5-17" y="15" solution="ATLANTSKI PAKT" is-theme="true"/><word id="40" x="1-3" y="16" solution="ESO" is-theme="true"/><word id="41" x="5-8" y="16" solution="VAJT" is-theme="true"/><word id="42" x="10-17" y="16" solution="ALASEHIR" is-theme="true"/><word id="43" x="1-3" y="17" solution="STR" is-theme="true"/><word id="44" x="5-8" y="17" solution="STEP" is-theme="true"/><word id="45" x="10-17" y="17" solution="ČAROVINA" is-theme="true"/><word id="46" x="1" y="1-5" solution="KVARK" is-theme="true"/><word id="47" x="2" y="1-5" solution="VAREŠ" is-theme="true"/><word id="48" x="3" y="1-5" solution="ARAME" is-theme="true"/><word id="49" x="4" y="1-3" solution="DIN" is-theme="true"/><word id="50" x="5" y="1-3" solution="ROD" is-theme="true"/><word id="51" x="6" y="1-4" solution="ILAM" is-theme="true"/><word id="52" x="7" y="1-4" solution="GIDE" is-theme="true"/><word id="53" x="8" y="1-4" solution="ATEJ" is-theme="true"/><word id="54" x="10" y="1-3" solution="IAU" is-theme="true"/><word id="55" x="11" y="1-7" solution="ZVEZDAN" is-theme="true"/><word id="56" x="12" y="1-7" solution="BARIERA" is-theme="true"/><word id="57" x="13" y="1-5" solution="ANOUK" is-theme="true"/><word id="58" x="15" y="1-11" solution="TOVARNA SANJ" is-theme="true"/><word id="59" x="16" y="1-7" solution="OVERATH" is-theme="true"/><word id="60" x="17" y="1-7" solution="PARAZOL" is-theme="true"/><word id="61" x="9" y="3-5" solution="DED" is-theme="true"/><word id="62" x="4" y="5-7" solution="FLN" is-theme="true"/><word id="63" x="5" y="5-10" solution="TISKAR" is-theme="true"/><word id="64" x="10" y="5-7" solution="EWE" is-theme="true"/><word id="65" x="14" y="5-9" solution="MODEM" is-theme="true"/><word id="66" x="6" y="6-9" solution="ŠKUD" is-theme="true"/><word id="67" x="7" y="6-9" solution="PAND" is-theme="true"/><word id="68" x="1" y="7-9" solution="ŠAC" is-theme="true"/><word id="69" x="2" y="7-9" solution="PEI" is-theme="true"/><word id="70" x="3" y="7-17" solution="ADULTERATOR" is-theme="true"/><word id="71" x="8" y="7-9" solution="SAE" is-theme="true"/><word id="72" x="9" y="7-11" solution="TRGAČ" is-theme="true"/><word id="73" x="13" y="8-13" solution="HENMAN" is-theme="true"/><word id="74" x="4" y="9-13" solution="DAIRE" is-theme="true"/><word id="75" x="10" y="9-11" solution="URE" is-theme="true"/><word id="76" x="11" y="9-12" solution="ABAK" is-theme="true"/><word id="77" x="12" y="9-12" solution="TURN" is-theme="true"/><word id="78" x="16" y="9-11" solution="LEE" is-theme="true"/><word id="79" x="17" y="9-11" solution="ARC" is-theme="true"/><word id="80" x="1" y="11-17" solution="BENARES" is-theme="true"/><word id="81" x="2" y="11-17" solution="ETATIST" is-theme="true"/><word id="82" x="6" y="11-17" solution="REOSTAT" is-theme="true"/><word id="83" x="7" y="11-17" solution="DIVULJE" is-theme="true"/><word id="84" x="8" y="11-13" solution="ESA" is-theme="true"/><word id="85" x="14" y="11-13" solution="EPI" is-theme="true"/><word id="86" x="5" y="13-17" solution="KNAVS" is-theme="true"/><word id="87" x="9" y="13-15" solution="JEN" is-theme="true"/><word id="88" x="15" y="13-17" solution="SPAHI" is-theme="true"/><word id="89" x="16" y="13-17" solution="ASKIN" is-theme="true"/><word id="90" x="17" y="13-17" solution="NITRA" is-theme="true"/><word id="91" x="10" y="14-17" solution="RTAČ" is-theme="true"/><word id="92" x="11" y="14-17" solution="ISLA" is-theme="true"/><word id="93" x="12" y="14-17" solution="EKAR" is-theme="true"/><word id="94" x="8" y="15-17" solution="ATP" is-theme="true"/><word id="95" x="13" y="15-17" solution="ISO" is-theme="true"/><word id="96" x="14" y="15-17" solution="PEV" is-theme="true"/><clues ordering="normal"><title><b>Across</b></title><clue word="1" number="1" citation="perplexity">voziček ali kočija, ki ga vlečejo štirje konji, nameščeni vzporedno v enem redu pri starih Rimljanih</clue><clue word="2" number="9" citation="perplexity">manjša soba, pogosto glavni stanovanjski prostor v kmečki hiši (knjiž.)</clue><clue word="3" number="13" citation="perplexity">orožje z daljšo cevjo za izstreljevanje granat</clue><clue word="4" number="16" citation="perplexity">vrsta vulkanske kamnine, ki vsebuje okrogle, glatke vključke različnih mineralov</clue><clue word="5" number="17" citation="perplexity">ime kanadskega igralca Jogia (1992-)</clue><clue word="6" number="18" citation="perplexity">jezero na jugu Turčije</clue><clue word="7" number="19" citation="perplexity">mesto v Španiji (tri besede)</clue><clue word="8" number="21" citation="perplexity">rimski cesar - Lucij Avrelij (130†169)</clue><clue word="9" number="22" citation="perplexity">po rimski mitologiji Romulov brat dvojček</clue><clue word="10" number="23" citation="perplexity">naselje v občini Cirkulane</clue><clue word="11" number="24" citation="perplexity">starogermansko ime boga Tyra</clue><clue word="12" number="25" citation="perplexity">predplačilo pri sklenitvi pogodbe</clue><clue word="13" number="26" citation="perplexity">trgovsko dejavnost ali posel, običajno tak, ki prinaša večji dobiček (pog.)</clue><clue word="14" number="29" citation="perplexity">v slovenski kulturi mitološki dobri mož, ki obdaruje otroke v tednu pred novim letom ali v noči z 31. decembra na 1. januar (dve besedi)</clue><clue word="15" number="32" citation="perplexity">nakit, lepotičje, okrasje ali glasno, razkošno okraševanje (star.)</clue><clue word="16" number="35" citation="perplexity">ameriška glasbena skupina (nekd.)</clue><clue word="17" number="36" citation="perplexity">jezero na Finskem</clue><clue word="18" number="37" citation="perplexity">zložljiva pregradna stena ali paravan, ki se uporablja za ustvarjanje zasebnosti v prostoru (dve besedi)</clue><clue word="19" number="42" citation="perplexity">ameriška igralka - Arlene (1928†2021)</clue><clue word="20" number="43" citation="perplexity">potujoči grški pevec in pesnik, Aojd</clue><clue word="21" number="44" citation="perplexity">lovec na kune (lov.)</clue><clue word="22" number="45" citation="perplexity">za polton znižani ton h (muz.)</clue><clue word="23" number="46" citation="perplexity">glavno mesto Gvatemale (orig.), (tri besede)</clue><clue word="24" number="53" citation="perplexity">v (rimski mitologiji) duh prednika, ki je bil zaščitnik družine, gospodinjstva in skupnosti</clue><clue word="25" number="54" citation="perplexity">morska riba iz družine šparov, ribon</clue><clue word="26" number="55" citation="perplexity">reka na Poljskem, desni pritok reke Warte, ki je ena od glavnih rek zahodne Poljske</clue><clue word="27" number="56" citation="perplexity">kamerunski pisatelj - Mongo (1932†2001), (Razvrat v misijonu Bomba)</clue><clue word="28" number="58" citation="perplexity">vojak Rdeče armade</clue><clue word="29" number="62" citation="perplexity">brezbarvna, dišeča in zelo vnetljiva tekočina</clue><clue word="30" number="63" citation="perplexity">za polton zvišani ton e (muz.)</clue><clue word="31" number="64" citation="perplexity">delavec, ki izkopava premog, rudo ali druge minerale v rudnikih; rudar (pog.)</clue><clue word="32" number="65" citation="perplexity">dvodelno ločilo, s katerim označujemo premi ali dobesedni govor, zaznamujemo navedke (lingv.)</clue><clue word="33" number="68" citation="perplexity">prvi mesec po hebrejskem (židovskem) koledarju</clue><clue word="34" number="72" citation="perplexity">oče</clue><clue word="35" number="73" citation="perplexity">legendarna nemška avtomobilska in motociklistična znamka, ustanovljena leta 1873 kot Neckarsulmer Strickmaschinen-Union (nekdaj)</clue><clue word="36" number="74" citation="perplexity">jezero na severu ZDA, četrto po velikosti</clue><clue word="37" number="78" citation="perplexity">črka grške abecede</clue><clue word="38" number="79" citation="perplexity">pogovorni, vulgaren izraz za zadnjico oziroma zadnji del telesa</clue><clue word="39" number="80" citation="perplexity">vojaška zveza nekaterih zahodnoevropskih držav in ZDA, NATO (polit.), (dve besedi)</clue><clue word="40" number="84" citation="perplexity">znamka čeških motorjev za speedway</clue><clue word="41" number="85" citation="perplexity">slovenski filmski snemalec - Slavo (1935†2022)</clue><clue word="42" number="86" citation="perplexity">mesto v zahodni Turčiji</clue><clue word="43" number="87" citation="perplexity">okrajšava za stran</clue><clue word="44" number="88" citation="perplexity">ples na jazz glasbo, pri katerem plesalec z udarjanjem s čevlji ob tla ustvarja posebno ritmično spremljavo</clue><clue word="45" number="89" citation="perplexity">naselje pri Tutinu, Srbija</clue></clues><clues ordering="normal"><title><b>Down</b></title><clue word="46" number="1" citation="perplexity">hipotetični elementarni delec, osnovni in nedeljivi gradnik snovi (fiz.)</clue><clue word="47" number="2" citation="perplexity">naselje v Bosni in Hercegovini</clue><clue word="48" number="3" citation="perplexity">mesto v zvezni državi Maranhao, Brazilija</clue><clue word="49" number="4" citation="perplexity">enota za občutljivost fotografskega materiala (fot.)</clue><clue word="50" number="5" citation="perplexity">skupnost potomcev istega prednika</clue><clue word="51" number="6" citation="perplexity">provinca ob meji z Irakom v zahodnem delu Irana</clue><clue word="52" number="7" citation="perplexity">francoski pisatelj - Andre, nobelovec leta 1947 (1869†1951), (Ozka vrata)</clue><clue word="53" number="8" citation="perplexity">ata, oče (nar.)</clue><clue word="54" number="9" citation="perplexity">kratica za mednarodno astronomsko zvezo</clue><clue word="55" number="10" citation="perplexity">ime slovenskega zdravnika, nevrologa Pirtoška (1956-)</clue><clue word="56" number="11" citation="perplexity">ovira ali pregrada, ki preprečuje ali omejuje gibanje, dostop ali napredovanje</clue><clue word="57" number="12" citation="perplexity">ime francoske igralke Aimee (1932†2024)</clue><clue word="58" number="13" citation="perplexity">drugo ime Hollywooda (ekspr.), (dve besedi)</clue><clue word="59" number="14" citation="perplexity">nemški nogometaš - Wolfgang (1943-) (nekd.)</clue><clue word="60" number="15" citation="perplexity">vrsta dežnika oziroma sončnika, ki se je uporabljal za zaščito pred soncem in kot modni dodatek (star.)</clue><clue word="61" number="20" citation="perplexity">stari oče</clue><clue word="62" number="27" citation="perplexity">kratica alžirske osvobodilne fronte</clue><clue word="63" number="28" citation="perplexity">oseba, ki se poklicno ukvarja s tiskarskim postopkom, torej prenašanjem odtisa tiskovnih elementov, kot so črke, slike, simboli ali besedilo, na tiskovno podlago (npr. papir, karton, plastiko)</clue><clue word="64" number="30" citation="perplexity">afriško ljudstvo, ki živi v Gani, Togu in Beninu</clue><clue word="65" number="31" citation="perplexity">elektronska naprava, ki pretvori digitalni signal v analogni in obratno, da omogoči prenos podatkov prek analognih komunikacijskih kanalov, kot so telefonske linije (elektr.)</clue><clue word="66" number="33" citation="perplexity">nekdanji italijanski srebrnik, kovani denar, ki je bil v obtoku od druge polovice 16. do konca 18. stoletja (num.)</clue><clue word="67" number="34" citation="perplexity">naselje v županiji Pešta, Madžarska</clue><clue word="68" number="37" citation="perplexity">zaklad (nar.)</clue><clue word="69" number="38" citation="perplexity">kitajsko-ameriški arhitekt - Ieoh Ming (1917†2019)</clue><clue word="70" number="39" citation="perplexity">oseba, ki nekaj ponareja ali dodaja nečisto ali neizvirno snov, da bi poslabšal ali spremenil kvaliteto izdelka</clue><clue word="71" number="40" citation="perplexity">stopinje za merjenje viskoznosti motornih olj</clue><clue word="72" number="41" citation="perplexity">močen podočnik pri zvereh</clue><clue word="73" number="45" citation="perplexity">britanski teniški igralec - Tim (1974-) (nekd.)</clue><clue word="74" number="47" citation="perplexity">glasbeni instrument, ki ima na obodu pritrjene kovinske ploščice, ki ob udarjanju zvonijo; to je vrsta tamburina ali bobnečka (muz.)</clue><clue word="75" number="48" citation="perplexity">škotski pevec – James “Midge” (1953–)</clue><clue word="76" number="49" citation="perplexity">pripomoček za mehanično računanje pri Rimljanih in Grkih</clue><clue word="77" number="50" citation="perplexity">cerkveni stolp, zvonik (pog.)</clue><clue word="78" number="51" citation="perplexity">ameriška pisateljica - Harper (1926†2016) (Ne ubijaj slavca)</clue><clue word="79" number="52" citation="perplexity">levi pritok reke Isere v Franciji</clue><clue word="80" number="56" citation="perplexity">nekdanje ime mesta Varanasi v zvezni državi Utar Pradeš, Indija</clue><clue word="81" number="57" citation="perplexity">oseba, ki zagovarja močno državno vlogo ali intervencijo, ki podpira ali verjame v etatizem kot politični ali ekonomski sistem</clue><clue word="82" number="58" citation="perplexity">regulator napetosti in električnega toka (elektr.)</clue><clue word="83" number="59" citation="perplexity">naselje pri Trogirju, Hrvaška</clue><clue word="84" number="60" citation="perplexity">(v grški mitologiji) boginja usode</clue><clue word="85" number="61" citation="perplexity">vzdevek nekdanjega španskega košarkarja San Epifania</clue><clue word="86" number="66" citation="perplexity">slovenski nogometaš - Aleksander (1975-) (nekd.)</clue><clue word="87" number="67" citation="perplexity">japonska denarna enota</clue><clue word="88" number="69" citation="perplexity">pripadnik konjeniške vojaške enote v osmanski vojski (zgod.)</clue><clue word="89" number="70" citation="perplexity">avstrijsko-ameriški igralec - Leon (1907†2005), (Hogan s Heroes)</clue><clue word="90" number="71" citation="perplexity">reka na Slovaškem</clue><clue word="91" number="75" citation="perplexity">luknjač (star.)</clue><clue word="92" number="76" citation="perplexity">španski jezuitski pisatelj - y Rojo, Jose Francisco de (1703†1781)</clue><clue word="93" number="77" citation="perplexity">slovenski gospodarstvenik in alpinist - Franc (1942-)</clue><clue word="94" number="81" citation="perplexity">teniška računalniška lestvica za moške</clue><clue word="95" number="82" citation="perplexity">kratica za Mednarodno organizacijo za standardizacijo</clue><clue word="96" number="83" citation="perplexity">petje, pesem (zastar.)</clue></clues></crossword></rectangular-puzzle></crossword-compiler-applet>
